{
  "persona": {
    "name": "Kenny Langie",
    "age": 35,
    "personality": "Compassionate and resilient, deeply empathetic towards children in need and motivated by personal experiences to make a difference.",
    "employment": "Mental Health Specialist",
    "notes": "Dedicated volunteer at Children's Hospital in Los Angeles for over 10 years, inspired by the loss of his grandfather.",
    "communication_style": "Open and heartfelt, emphasizes personal connection and the need for joy and love in giving."
  }
}