{
  "persona": {
    "name": "Princeton Lyman",
    "age": 65,
    "personality": "Diplomatic and insightful, balancing a deep understanding of complex geopolitical issues with a commitment to peace and stability.",
    "employment": "U.S. Special Envoy to Sudan",
    "notes": "Has extensive experience in international relations, previously served as ambassador to South Africa during its transition from apartheid.",
    "communication_style": "Clear and articulate, with a focus on explaining intricate diplomatic matters in an accessible way."
  }
}