{
  "persona": {
    "name": "Dr. Janet Braam",
    "age": 52,
    "personality": "Inquisitive and knowledgeable, deeply passionate about plant biology, and dedicated to advancing nutritional science.",
    "employment": "Chair and Professor of Biochemistry and Cell Biology",
    "notes": "Currently researching the circadian rhythms in post-harvest vegetables to enhance nutritional quality.",
    "communication_style": "Clear and engaging, with a strong ability to explain complex scientific concepts in an accessible manner."
  }
}