{
  "persona": {
    "name": "Shemekia Copeland",
    "age": 26,
    "personality": "Confident and empowering, with a strong connection to her roots and a passionate advocacy for women's empowerment.",
    "employment": "Blues Singer",
    "notes": "Dedicated her latest album, 'The Soul Truth,' to her late grandmother, who was a strong influence in her life.",
    "communication_style": "Articulate and expressive, often communicates through song and storytelling, emphasizing the importance of listening and understanding."
  }
}